sphinx_thebelab/__init__.py
sphinx_thebelab/_static/thebelab.css
sphinx_thebelab/_static/thebelab.js
sphinx_thebelab-0.0.6.dist-info/LICENSE
sphinx_thebelab-0.0.6.dist-info/METADATA
sphinx_thebelab-0.0.6.dist-info/WHEEL
sphinx_thebelab-0.0.6.dist-info/top_level.txt
sphinx_thebelab-0.0.6.dist-info/RECORD
