Metadata-Version: 2.1
Name: sphinx-thebelab
Version: 0.0.6
Summary: Add a copy button to each of your code cells.
Home-page: https://github.com/executablebooks/sphinx-thebelab
Author: Executable Book Project
License: MIT License
Platform: UNKNOWN
Classifier: License :: OSI Approved :: MIT License
Requires-Dist: sphinx (>=1.8)
Provides-Extra: sphinx
Requires-Dist: myst-parser[sphinx] ; extra == 'sphinx'
Requires-Dist: sphinx-book-theme ; extra == 'sphinx'
Provides-Extra: testing
Requires-Dist: pytest ; extra == 'testing'
Requires-Dist: pytest-regressions ; extra == 'testing'
Requires-Dist: beautifulsoup4 ; extra == 'testing'
